argparse_utils/__init__.py
argparse_utils_tddschn-0.3.1.dist-info/METADATA
argparse_utils_tddschn-0.3.1.dist-info/WHEEL
argparse_utils_tddschn-0.3.1.dist-info/licenses/LICENSE
argparse_utils_tddschn-0.3.1.dist-info/RECORD
