Metadata-Version: 2.4
Name: argparse-utils-tddschn
Version: 0.3.1
Summary: A utility library to dynamically remove and rename arguments from argparse.ArgumentParser objects.
Project-URL: Homepage, https://github.com/tddschn/argparse-utils-tddschn
Project-URL: Issues, https://github.com/tddschn/argparse-utils-tddschn/issues
Author-email: Teddy Xinyuan Chen <45612704+tddschn@users.noreply.github.com>
License-File: LICENSE
Classifier: License :: OSI Approved :: MIT License
Classifier: Operating System :: OS Independent
Classifier: Programming Language :: Python :: 3
Classifier: Topic :: Software Development :: Libraries :: Python Modules
Requires-Python: >=3.8
Provides-Extra: dev
Requires-Dist: pytest>=7.0; extra == 'dev'
